pysfcgal/__init__.py
pysfcgal/_sfcgal.abi3.so
pysfcgal/sfcgal.py
pysfcgal/sfcgal_build.py
pysfcgal/sfcgal_def.c
pysfcgal/sfcgal_def_msvc.c
pysfcgal.libs/libSFCGAL-e9a26dd4.so.2.2.0
pysfcgal.libs/libboost_serialization-28b9a3d2.so.1.74.0
pysfcgal.libs/libgmp-7376c9af.so.10.4.1
pysfcgal.libs/libgmpxx-8b7fb94a.so.4.6.1
pysfcgal.libs/libmpfr-699a9c25.so.6.2.0
pysfcgal-2.2.0.dist-info/METADATA
pysfcgal-2.2.0.dist-info/WHEEL
pysfcgal-2.2.0.dist-info/top_level.txt
pysfcgal-2.2.0.dist-info/RECORD
